OAQuant0129/PE/res.v
module res(
    input wire clk,
    input wire rst_n,
    input wire start,      // 复位写地址计数器和乒乓状态
    // input wire pingpang, // [修改] 移除外部输入
    
    // 来自脉动阵列的输入
    input wire [511:0] array_data_in, 
    input wire array_valid_in,

    // SRAM 写端口
    output reg bce0, bce1, bce2, bce3, bce4, bce5, bce6, bce7,
    output reg [14:0] bwaddr0, bwaddr1, bwaddr2, bwaddr3, bwaddr4, bwaddr5, bwaddr6, bwaddr7,
    output reg [127:0] bwdata0, bwdata1, bwdata2, bwdata3, bwdata4, bwdata5, bwdata6, bwdata7
);

    // 参数定义
    parameter COL_NUM    = 32;
    parameter DATA_WIDTH = 16;
    parameter SKEW_DELAY = COL_NUM - 1; // 31
    
    // [修改] 新增 Bank 深度定义
    parameter BANK_DEPTH = 2048; // 2k

    // ============================================================
    // 1. 反向三角形延时 (De-skew Unit)
    // ============================================================
    
    wire [511:0] aligned_data; // 对齐后的一整行数据
    wire aligned_valid;        
    
    genvar i;
    generate
        for (i = 0; i < COL_NUM; i = i + 1) begin : deskew_logic
            // 提取当前列的数据
            wire [DATA_WIDTH-1:0] col_in_data;
            assign col_in_data = array_data_in[(i+1)*DATA_WIDTH-1 : i*DATA_WIDTH];

            // 计算需要的延时深度
            localparam DELAY_DEPTH = SKEW_DELAY - i;

            if (DELAY_DEPTH == 0) begin
                assign aligned_data[(i+1)*DATA_WIDTH-1 : i*DATA_WIDTH] = col_in_data;
            end else begin
                reg [DATA_WIDTH-1:0] delay_regs [0:DELAY_DEPTH-1];
                integer j;

                always @(posedge clk or negedge rst_n) begin
                    if (!rst_n) begin
                        for (j = 0; j < DELAY_DEPTH; j = j + 1) delay_regs[j] <= 0;
                    end else begin
                        delay_regs[0] <= col_in_data;
                        for (j = 1; j < DELAY_DEPTH; j = j + 1) begin
                            delay_regs[j] <= delay_regs[j-1];
                        end
                    end
                end
                assign aligned_data[(i+1)*DATA_WIDTH-1 : i*DATA_WIDTH] = delay_regs[DELAY_DEPTH-1];
            end
        end
    endgenerate

    // ============================================================
    // Valid 信号同步延时
    // ============================================================
    reg [SKEW_DELAY-1:0] valid_pipe; 

    always @(posedge clk or negedge rst_n) begin
        if (!rst_n) begin
            valid_pipe <= 0;
        end else begin
            // 移位逻辑
            valid_pipe[SKEW_DELAY-1:1] <= valid_pipe[SKEW_DELAY-2:0];
            valid_pipe[0] <= array_valid_in;
        end
    end

    assign aligned_valid = valid_pipe[SKEW_DELAY-1] && array_valid_in;

    // ============================================================
    // 2. 地址产生与数据分发 (SRAM Writer)
    // ============================================================
    
    reg [10:0] write_cnt; 
    reg pingpang; // [修改] 内部定义乒乓寄存器

    always @(posedge clk or negedge rst_n) begin
        if (!rst_n) begin
            write_cnt <= 0;
            pingpang  <= 0;
            {bce0, bce1, bce2, bce3, bce4, bce5, bce6, bce7} <= 0;
            bwaddr0 <= 0; bwaddr1 <= 0; bwaddr2 <= 0; bwaddr3 <= 0;
            bwaddr4 <= 0; bwaddr5 <= 0; bwaddr6 <= 0; bwaddr7 <= 0;
            bwdata0 <= 0; bwdata1 <= 0; bwdata2 <= 0; bwdata3 <= 0;
            bwdata4 <= 0; bwdata5 <= 0; bwdata6 <= 0; bwdata7 <= 0;
        end else begin
            // 默认拉低写使能
            {bce0, bce1, bce2, bce3, bce4, bce5, bce6, bce7} <= 0;

            if (start) begin
                write_cnt <= 0;
                pingpang  <= 0; // [修改] Start 信号复位 PingPang 状态 (默认先写 Bank0-3)
            end
            
            if (aligned_valid) begin
                
                // [修改] 地址与 PingPang 翻转逻辑
                if (write_cnt == BANK_DEPTH - 1) begin // 到达 2047
                    write_cnt <= 0;        // 归零
                    pingpang  <= ~pingpang; // 翻转
                end else begin
                    write_cnt <= write_cnt + 1'b1;
                end

                // 写操作 (注意：这里使用的是当前拍尚未更新的 pingpang 和 write_cnt)
                // 例如：当 write_cnt=2047 时，这里依然用 2047 写当前 Bank，下一拍才会翻转
                if (!pingpang) begin
                    // ---- 写 Ping 区 (Bank 0-3) ----
                    bce0 <= 1; bce1 <= 1; bce2 <= 1; bce3 <= 1;
                    
                    bwaddr0 <= {write_cnt, 4'b0000};
                    bwaddr1 <= {write_cnt, 4'b0000};
                    bwaddr2 <= {write_cnt, 4'b0000};
                    bwaddr3 <= {write_cnt, 4'b0000};
                    
                    bwdata0 <= aligned_data[127:0];
                    bwdata1 <= aligned_data[255:128];
                    bwdata2 <= aligned_data[383:256];
                    bwdata3 <= aligned_data[511:384];
                end else begin
                    // ---- 写 Pong 区 (Bank 4-7) ----
                    bce4 <= 1; bce5 <= 1; bce6 <= 1; bce7 <= 1;

                    bwaddr4 <= {write_cnt, 4'b0000};
                    bwaddr5 <= {write_cnt, 4'b0000};
                    bwaddr6 <= {write_cnt, 4'b0000};
                    bwaddr7 <= {write_cnt, 4'b0000};

                    bwdata4 <= aligned_data[127:0];
                    bwdata5 <= aligned_data[255:128];
                    bwdata6 <= aligned_data[383:256];
                    bwdata7 <= aligned_data[511:384];
                end
            end
        end
    end

endmodule

OAQuant0123/tb/tb_res.v
`timescale 1ns/1ps

module tb_res;

    // =======================================================
    // 1. 参数定义
    // =======================================================
    parameter COL_NUM    = 32;
    parameter DATA_WIDTH = 16;
    parameter SKEW_DELAY = 31;
    parameter BANK_DEPTH = 2048;

    // =======================================================
    // 2. 信号声明
    // =======================================================
    reg clk;
    reg rst_n;
    reg start;
    
    // 输入
    reg [511:0] array_data_in;
    reg array_valid_in;

    // 输出
    wire bce0, bce1, bce2, bce3, bce4, bce5, bce6, bce7;
    wire [14:0] bwaddr0, bwaddr1, bwaddr2, bwaddr3, bwaddr4, bwaddr5, bwaddr6, bwaddr7;
    wire [127:0] bwdata0, bwdata1, bwdata2, bwdata3, bwdata4, bwdata5, bwdata6, bwdata7;

    integer i;

    // =======================================================
    // 3. DUT 例化
    // =======================================================
    res #(
        .COL_NUM(COL_NUM),
        .DATA_WIDTH(DATA_WIDTH),
        .BANK_DEPTH(BANK_DEPTH)
    ) u_dut (
        .clk(clk),
        .rst_n(rst_n),
        .start(start),
        .array_data_in(array_data_in),
        .array_valid_in(array_valid_in),
        
        .bce0(bce0), .bce1(bce1), .bce2(bce2), .bce3(bce3),
        .bce4(bce4), .bce5(bce5), .bce6(bce6), .bce7(bce7),
        
        .bwaddr0(bwaddr0), .bwaddr1(bwaddr1), .bwaddr2(bwaddr2), .bwaddr3(bwaddr3),
        .bwaddr4(bwaddr4), .bwaddr5(bwaddr5), .bwaddr6(bwaddr6), .bwaddr7(bwaddr7),
        
        .bwdata0(bwdata0), .bwdata1(bwdata1), .bwdata2(bwdata2), .bwdata3(bwdata3),
        .bwdata4(bwdata4), .bwdata5(bwdata5), .bwdata6(bwdata6), .bwdata7(bwdata7)
    );

    // =======================================================
    // 4. 时钟生成
    // =======================================================
    initial clk = 0;
    always #5 clk = ~clk;

    // =======================================================
    // 5. 核心任务：模拟脉动阵列的波浪输出
    // =======================================================
    // num_rows: 要发送的总行数 (例如 8 行)
    task drive_systolic_wave;
        input integer num_rows;
        integer t_step;
        integer row_idx;
        begin
            $display("Starting Systolic Wave Drive for %0d rows...", num_rows);
            
            // 在任务开始时，先同步到下一个时钟上升沿，确保从干净的状态开始
            @(posedge clk);
            
            // 脉动阵列的总活动时间 = 行数 + Skew时间 (31)
            // 我们多跑几拍以确保波形完整
            for (t_step = 0; t_step < num_rows + SKEW_DELAY + 5; t_step = t_step + 1) begin
                
                // --- 1. 生成 Valid 信号 ---
                // 使用非阻塞赋值 (<=)，信号会在当前时钟沿后更新，并保持到下一个时钟沿
                if (t_step < num_rows + SKEW_DELAY) 
                    array_valid_in <= 1'b1;
                else 
                    array_valid_in <= 1'b0;

                // --- 2. 生成 Skewed Data ---
                for (i = 0; i < COL_NUM; i = i + 1) begin
                    row_idx = t_step - i;

                    if (row_idx >= 0 && row_idx < num_rows) begin
                        array_data_in[i*DATA_WIDTH +: DATA_WIDTH] <= row_idx + 1;
                    end else begin
                        array_data_in[i*DATA_WIDTH +: DATA_WIDTH] <= 16'd0;
                    end
                end

                // [关键] 等待这一个时钟周期结束，迈向下一个周期
                @(posedge clk); 
            end
            
            // 结束后清零 (再过一拍)
            array_data_in <= 0;
            array_valid_in <= 0;
            @(posedge clk);
        end
    endtask

    // =======================================================
    // 6. 主测试流程
    // =======================================================
    initial begin
        $dumpfile("res.vcd");
        $dumpvars(0, tb_res);

        // 初始化
        rst_n = 0;
        start = 0;
        array_data_in = 0;
        array_valid_in = 0;

        // 复位释放
        #20 rst_n = 1;
        #10 start = 1; // 复位内部计数器和PingPang
        #10 start = 0;

        // --- 发送 8 行数据 ---
        // 期望结果：
        // 在大概 T=32 左右，SRAM 写入端口开始动作
        // 第一拍写入全 1
        // 第二拍写入全 2
        // ... 直到全 8
        drive_systolic_wave(8);

        #100;
        $finish;
    end
    
    // =======================================================
    // 7. 自动监控与打印
    // =======================================================
    // 监控 Bank0 的写入数据，看是否对齐
    always @(posedge clk) begin
        if (u_dut.aligned_valid) begin // 只有当模块认为对齐有效时才打印
            $display("[Time %0t] SRAM Write! Bank0 Data (Low 16b): %0d | Bank7 Data (Low 16b): %0d", 
                     $time, u_dut.bwdata0[15:0], u_dut.bwdata7[15:0]);
            
            // 检查对齐：Bank0 和 Bank7 的数据必须相等
            if (u_dut.bwdata0[15:0] !== u_dut.bwdata7[15:0]) begin
                $display("    ERROR: Mismatch! De-skew failed. Col 0 and Col 31 are not aligned.");
            end else begin
                $display("    OK: Data aligned.");
            end
        end
    end

endmodule

OAQuant0123/PE/res.vcd
$date
	Wed Jan 28 00:47:34 2026
$end
$version
	Icarus Verilog
$end
$timescale
	1ps
$end
$scope module tb_res $end
$var wire 128 ! bwdata7 [127:0] $end
$var wire 128 " bwdata6 [127:0] $end
$var wire 128 # bwdata5 [127:0] $end
$var wire 128 $ bwdata4 [127:0] $end
$var wire 128 % bwdata3 [127:0] $end
$var wire 128 & bwdata2 [127:0] $end
$var wire 128 ' bwdata1 [127:0] $end
$var wire 128 ( bwdata0 [127:0] $end
$var wire 15 ) bwaddr7 [14:0] $end
$var wire 15 * bwaddr6 [14:0] $end
$var wire 15 + bwaddr5 [14:0] $end
$var wire 15 , bwaddr4 [14:0] $end
$var wire 15 - bwaddr3 [14:0] $end
$var wire 15 . bwaddr2 [14:0] $end
$var wire 15 / bwaddr1 [14:0] $end
$var wire 15 0 bwaddr0 [14:0] $end
$var wire 1 1 bce7 $end
$var wire 1 2 bce6 $end
$var wire 1 3 bce5 $end
$var wire 1 4 bce4 $end
$var wire 1 5 bce3 $end
$var wire 1 6 bce2 $end
$var wire 1 7 bce1 $end
$var wire 1 8 bce0 $end
$var parameter 32 9 BANK_DEPTH $end
$var parameter 32 : COL_NUM $end
$var parameter 32 ; DATA_WIDTH $end
$var parameter 32 < SKEW_DELAY $end
$var reg 512 = array_data_in [511:0] $end
$var reg 1 > array_valid_in $end
$var reg 1 ? clk $end
$var reg 1 @ rst_n $end
$var reg 1 A start $end
$var integer 32 B i [31:0] $end
$scope module u_dut $end
$var wire 1 C aligned_valid $end
$var wire 512 D array_data_in [511:0] $end
$var wire 1 > array_valid_in $end
$var wire 1 ? clk $end
$var wire 1 @ rst_n $end
$var wire 1 A start $end
$var wire 512 E aligned_data [511:0] $end
$var parameter 32 F BANK_DEPTH $end
$var parameter 32 G COL_NUM $end
$var parameter 32 H DATA_WIDTH $end
$var parameter 33 I SKEW_DELAY $end
$var reg 1 8 bce0 $end
$var reg 1 7 bce1 $end
$var reg 1 6 bce2 $end
$var reg 1 5 bce3 $end
$var reg 1 4 bce4 $end
$var reg 1 3 bce5 $end
$var reg 1 2 bce6 $end
$var reg 1 1 bce7 $end
$var reg 15 J bwaddr0 [14:0] $end
$var reg 15 K bwaddr1 [14:0] $end
$var reg 15 L bwaddr2 [14:0] $end
$var reg 15 M bwaddr3 [14:0] $end
$var reg 15 N bwaddr4 [14:0] $end
$var reg 15 O bwaddr5 [14:0] $end
$var reg 15 P bwaddr6 [14:0] $end
$var reg 15 Q bwaddr7 [14:0] $end
$var reg 128 R bwdata0 [127:0] $end
$var reg 128 S bwdata1 [127:0] $end
$var reg 128 T bwdata2 [127:0] $end
$var reg 128 U bwdata3 [127:0] $end
$var reg 128 V bwdata4 [127:0] $end
$var reg 128 W bwdata5 [127:0] $end
$var reg 128 X bwdata6 [127:0] $end
$var reg 128 Y bwdata7 [127:0] $end
$var reg 1 Z pingpang $end
$var reg 31 [ valid_pipe [30:0] $end
$var reg 11 \ write_cnt [10:0] $end
$scope begin deskew_logic[0] $end
$var wire 16 ] col_in_data [15:0] $end
$var parameter 32 ^ DELAY_DEPTH $end
$var parameter 2 _ i $end
$scope begin genblk1 $end
$var integer 32 ` j [31:0] $end
$upscope $end
$upscope $end
$scope begin deskew_logic[1] $end
$var wire 16 a col_in_data [15:0] $end
$var parameter 32 b DELAY_DEPTH $end
$var parameter 2 c i $end
$scope begin genblk1 $end
$var integer 32 d j [31:0] $end
$upscope $end
$upscope $end
$scope begin deskew_logic[2] $end
$var wire 16 e col_in_data [15:0] $end
$var parameter 32 f DELAY_DEPTH $end
$var parameter 3 g i $end
$scope begin genblk1 $end
$var integer 32 h j [31:0] $end
$upscope $end
$upscope $end
$scope begin deskew_logic[3] $end
$var wire 16 i col_in_data [15:0] $end
$var parameter 32 j DELAY_DEPTH $end
$var parameter 3 k i $end
$scope begin genblk1 $end
$var integer 32 l j [31:0] $end
$upscope $end
$upscope $end
$scope begin deskew_logic[4] $end
$var wire 16 m col_in_data [15:0] $end
$var parameter 32 n DELAY_DEPTH $end
$var parameter 4 o i $end
$scope begin genblk1 $end
$var integer 32 p j [31:0] $end
$upscope $end
$upscope $end
$scope begin deskew_logic[5] $end
$var wire 16 q col_in_data [15:0] $end
$var parameter 32 r DELAY_DEPTH $end
$var parameter 4 s i $end
$scope begin genblk1 $end
$var integer 32 t j [31:0] $end
$upscope $end
$upscope $end
$scope begin deskew_logic[6] $end
$var wire 16 u col_in_data [15:0] $end
$var parameter 32 v DELAY_DEPTH $end
$var parameter 4 w i $end
$scope begin genblk1 $end
$var integer 32 x j [31:0] $end
$upscope $end
$upscope $end
$scope begin deskew_logic[7] $end
$var wire 16 y col_in_data [15:0] $end
$var parameter 32 z DELAY_DEPTH $end
$var parameter 4 { i $end
$scope begin genblk1 $end
$var integer 32 | j [31:0] $end
$upscope $end
$upscope $end
$scope begin deskew_logic[8] $end
$var wire 16 } col_in_data [15:0] $end
$var parameter 32 ~ DELAY_DEPTH $end
$var parameter 5 !" i $end
$scope begin genblk1 $end
$var integer 32 "" j [31:0] $end
$upscope $end
$upscope $end
$scope begin deskew_logic[9] $end
$var wire 16 #" col_in_data [15:0] $end
$var parameter 32 $" DELAY_DEPTH $end
$var parameter 5 %" i $end
$scope begin genblk1 $end
$var integer 32 &" j [31:0] $end
$upscope $end
$upscope $end
$scope begin deskew_logic[10] $end
$var wire 16 '" col_in_data [15:0] $end
$var parameter 32 (" DELAY_DEPTH $end
$var parameter 5 )" i $end
$scope begin genblk1 $end
$var integer 32 *" j [31:0] $end
$upscope $end
$upscope $end
$scope begin deskew_logic[11] $end
$var wire 16 +" col_in_data [15:0] $end
$var parameter 32 ," DELAY_DEPTH $end
$var parameter 5 -" i $end
$scope begin genblk1 $end
$var integer 32 ." j [31:0] $end
$upscope $end
$upscope $end
$scope begin deskew_logic[12] $end
$var wire 16 /" col_in_data [15:0] $end
$var parameter 32 0" DELAY_DEPTH $end
$var parameter 5 1" i $end
$scope begin genblk1 $end
$var integer 32 2" j [31:0] $end
$upscope $end
$upscope $end
$scope begin deskew_logic[13] $end
$var wire 16 3" col_in_data [15:0] $end
$var parameter 32 4" DELAY_DEPTH $end
$var parameter 5 5" i $end
$scope begin genblk1 $end
$var integer 32 6" j [31:0] $end
$upscope $end
$upscope $end
$scope begin deskew_logic[14] $end
$var wire 16 7" col_in_data [15:0] $end
$var parameter 32 8" DELAY_DEPTH $end
$var parameter 5 9" i $end
$scope begin genblk1 $end
$var integer 32 :" j [31:0] $end
$upscope $end
$upscope $end
$scope begin deskew_logic[15] $end
$var wire 16 ;" col_in_data [15:0] $end
$var parameter 32 <" DELAY_DEPTH $end
$var parameter 5 =" i $end
$scope begin genblk1 $end
$var integer 32 >" j [31:0] $end
$upscope $end
$upscope $end
$scope begin deskew_logic[16] $end
$var wire 16 ?" col_in_data [15:0] $end
$var parameter 32 @" DELAY_DEPTH $end
$var parameter 6 A" i $end
$scope begin genblk1 $end
$var integer 32 B" j [31:0] $end
$upscope $end
$upscope $end
$scope begin deskew_logic[17] $end
$var wire 16 C" col_in_data [15:0] $end
$var parameter 32 D" DELAY_DEPTH $end
$var parameter 6 E" i $end
$scope begin genblk1 $end
$var integer 32 F" j [31:0] $end
$upscope $end
$upscope $end
$scope begin deskew_logic[18] $end
$var wire 16 G" col_in_data [15:0] $end
$var parameter 32 H" DELAY_DEPTH $end
$var parameter 6 I" i $end
$scope begin genblk1 $end
$var integer 32 J" j [31:0] $end
$upscope $end
$upscope $end
$scope begin deskew_logic[19] $end
$var wire 16 K" col_in_data [15:0] $end
$var parameter 32 L" DELAY_DEPTH $end
$var parameter 6 M" i $end
$scope begin genblk1 $end
$var integer 32 N" j [31:0] $end
$upscope $end
$upscope $end
$scope begin deskew_logic[20] $end
$var wire 16 O" col_in_data [15:0] $end
$var parameter 32 P" DELAY_DEPTH $end
$var parameter 6 Q" i $end
$scope begin genblk1 $end
$var integer 32 R" j [31:0] $end
$upscope $end
$upscope $end
$scope begin deskew_logic[21] $end
$var wire 16 S" col_in_data [15:0] $end
$var parameter 32 T" DELAY_DEPTH $end
$var parameter 6 U" i $end
$scope begin genblk1 $end
$var integer 32 V" j [31:0] $end
$upscope $end
$upscope $end
$scope begin deskew_logic[22] $end
$var wire 16 W" col_in_data [15:0] $end
$var parameter 32 X" DELAY_DEPTH $end
$var parameter 6 Y" i $end
$scope begin genblk1 $end
$var integer 32 Z" j [31:0] $end
$upscope $end
$upscope $end
$scope begin deskew_logic[23] $end
$var wire 16 [" col_in_data [15:0] $end
$var parameter 32 \" DELAY_DEPTH $end
$var parameter 6 ]" i $end
$scope begin genblk1 $end
$var integer 32 ^" j [31:0] $end
$upscope $end
$upscope $end
$scope begin deskew_logic[24] $end
$var wire 16 _" col_in_data [15:0] $end
$var parameter 32 `" DELAY_DEPTH $end
$var parameter 6 a" i $end
$scope begin genblk1 $end
$var integer 32 b" j [31:0] $end
$upscope $end
$upscope $end
$scope begin deskew_logic[25] $end
$var wire 16 c" col_in_data [15:0] $end
$var parameter 32 d" DELAY_DEPTH $end
$var parameter 6 e" i $end
$scope begin genblk1 $end
$var integer 32 f" j [31:0] $end
$upscope $end
$upscope $end
$scope begin deskew_logic[26] $end
$var wire 16 g" col_in_data [15:0] $end
$var parameter 32 h" DELAY_DEPTH $end
$var parameter 6 i" i $end
$scope begin genblk1 $end
$var integer 32 j" j [31:0] $end
$upscope $end
$upscope $end
$scope begin deskew_logic[27] $end
$var wire 16 k" col_in_data [15:0] $end
$var parameter 32 l" DELAY_DEPTH $end
$var parameter 6 m" i $end
$scope begin genblk1 $end
$var integer 32 n" j [31:0] $end
$upscope $end
$upscope $end
$scope begin deskew_logic[28] $end
$var wire 16 o" col_in_data [15:0] $end
$var parameter 32 p" DELAY_DEPTH $end
$var parameter 6 q" i $end
$scope begin genblk1 $end
$var integer 32 r" j [31:0] $end
$upscope $end
$upscope $end
$scope begin deskew_logic[29] $end
$var wire 16 s" col_in_data [15:0] $end
$var parameter 32 t" DELAY_DEPTH $end
$var parameter 6 u" i $end
$scope begin genblk1 $end
$var integer 32 v" j [31:0] $end
$upscope $end
$upscope $end
$scope begin deskew_logic[30] $end
$var wire 16 w" col_in_data [15:0] $end
$var parameter 32 x" DELAY_DEPTH $end
$var parameter 6 y" i $end
$scope begin genblk1 $end
$var integer 32 z" j [31:0] $end
$upscope $end
$upscope $end
$scope begin deskew_logic[31] $end
$var wire 16 {" col_in_data [15:0] $end
$var parameter 32 |" DELAY_DEPTH $end
$var parameter 6 }" i $end
$scope begin genblk1 $end
$upscope $end
$upscope $end
$upscope $end
$scope task drive_systolic_wave $end
$var integer 32 ~" num_rows [31:0] $end
$var integer 32 !# row_idx [31:0] $end
$var integer 32 "# t_step [31:0] $end
$upscope $end
$upscope $end
$enddefinitions $end
$comment Show the parameter values. $end
$dumpall
b11111 }"
b0 |"
b11110 y"
b1 x"
b11101 u"
b10 t"
b11100 q"
b11 p"
b11011 m"
b100 l"
b11010 i"
b101 h"
b11001 e"
b110 d"
b11000 a"
b111 `"
b10111 ]"
b1000 \"
b10110 Y"
b1001 X"
b10101 U"
b1010 T"
b10100 Q"
b1011 P"
b10011 M"
b1100 L"
b10010 I"
b1101 H"
b10001 E"
b1110 D"
b10000 A"
b1111 @"
b1111 ="
b10000 <"
b1110 9"
b10001 8"
b1101 5"
b10010 4"
b1100 1"
b10011 0"
b1011 -"
b10100 ,"
b1010 )"
b10101 ("
b1001 %"
b10110 $"
b1000 !"
b10111 ~
b111 {
b11000 z
b110 w
b11001 v
b101 s
b11010 r
b100 o
b11011 n
b11 k
b11100 j
b10 g
b11101 f
b1 c
b11110 b
b0 _
b11111 ^
b11111 I
b10000 H
b100000 G
b100000000000 F
b11111 <
b10000 ;
b100000 :
b100000000000 9
$end
#0
$dumpvars
bx "#
bx !#
bx ~"
b0 {"
b1 z"
b0 w"
b10 v"
b0 s"
b11 r"
b0 o"
b100 n"
b0 k"
b101 j"
b0 g"
b110 f"
b0 c"
b111 b"
b0 _"
b1000 ^"
b0 ["
b1001 Z"
b0 W"
b1010 V"
b0 S"
b1011 R"
b0 O"
b1100 N"
b0 K"
b1101 J"
b0 G"
b1110 F"
b0 C"
b1111 B"
b0 ?"
b10000 >"
b0 ;"
b10001 :"
b0 7"
b10010 6"
b0 3"
b10011 2"
b0 /"
b10100 ."
b0 +"
b10101 *"
b0 '"
b10110 &"
b0 #"
b10111 ""
b0 }
b11000 |
b0 y
b11001 x
b0 u
b11010 t
b0 q
b11011 p
b0 m
b11100 l
b0 i
b11101 h
b0 e
b11110 d
b0 a
b11111 `
b0 ]
b0 \
b0 [
0Z
b0 Y
b0 X
b0 W
b0 V
b0 U
b0 T
b0 S
b0 R
b0 Q
b0 P
b0 O
b0 N
b0 M
b0 L
b0 K
b0 J
b0 E
b0 D
0C
bx B
0A
0@
0?
0>
b0 =
08
07
06
05
04
03
02
01
b0 0
b0 /
b0 .
b0 -
b0 ,
b0 +
b0 *
b0 )
b0 (
b0 '
b0 &
b0 %
b0 $
b0 #
b0 "
b0 !
$end
#5000
b1 z"
b10 v"
b11 r"
b100 n"
b101 j"
b110 f"
b111 b"
b1000 ^"
b1001 Z"
b1010 V"
b1011 R"
b1100 N"
b1101 J"
b1110 F"
b1111 B"
b10000 >"
b10001 :"
b10010 6"
b10011 2"
b10100 ."
b10101 *"
b10110 &"
b10111 ""
b11000 |
b11001 x
b11010 t
b11011 p
b11100 l
b11101 h
b11110 d
b11111 `
1?
#10000
0?
#15000
b11111 `
b11110 d
b11101 h
b11100 l
b11011 p
b11010 t
b11001 x
b11000 |
b10111 ""
b10110 &"
b10101 *"
b10100 ."
b10011 2"
b10010 6"
b10001 :"
b10000 >"
b1111 B"
b1110 F"
b1101 J"
b1100 N"
b1011 R"
b1010 V"
b1001 Z"
b1000 ^"
b111 b"
b110 f"
b101 j"
b100 n"
b11 r"
b10 v"
b1 z"
1?
#20000
0?
1@
#25000
b10 v"
b11 r"
b100 n"
b101 j"
b110 f"
b111 b"
b1000 ^"
b1001 Z"
b1010 V"
b1011 R"
b1100 N"
b1101 J"
b1110 F"
b1111 B"
b10000 >"
b10001 :"
b10010 6"
b10011 2"
b10100 ."
b10101 *"
b10110 &"
b10111 ""
b11000 |
b11001 x
b11010 t
b11011 p
b11100 l
b11101 h
b11110 d
b11111 `
1?
#30000
0?
1A
#35000
b11111 `
b11110 d
b11101 h
b11100 l
b11011 p
b11010 t
b11001 x
b11000 |
b10111 ""
b10110 &"
b10101 *"
b10100 ."
b10011 2"
b10010 6"
b10001 :"
b10000 >"
b1111 B"
b1110 F"
b1101 J"
b1100 N"
b1011 R"
b1010 V"
b1001 Z"
b1000 ^"
b111 b"
b110 f"
b101 j"
b100 n"
b11 r"
b10 v"
1?
#40000
0?
b1000 ~"
0A
#45000
b1 ]
b1 =
b1 D
1>
b10 v"
b11 r"
b100 n"
b101 j"
b110 f"
b111 b"
b1000 ^"
b1001 Z"
b1010 V"
b1011 R"
b1100 N"
b1101 J"
b1110 F"
b1111 B"
b10000 >"
b10001 :"
b10010 6"
b10011 2"
b10100 ."
b10101 *"
b10110 &"
b10111 ""
b11000 |
b11001 x
b11010 t
b11011 p
b11100 l
b11101 h
b11110 d
b11111 `
b11111111111111111111111111100001 !#
b100000 B
b0 "#
1?
#50000
0?
#55000
b1 a
b10 ]
b1 [
b10000000000000010 =
b10000000000000010 D
b11111 `
b11110 d
b11101 h
b11100 l
b11011 p
b11010 t
b11001 x
b11000 |
b10111 ""
b10110 &"
b10101 *"
b10100 ."
b10011 2"
b10010 6"
b10001 :"
b10000 >"
b1111 B"
b1110 F"
b1101 J"
b1100 N"
b1011 R"
b1010 V"
b1001 Z"
b1000 ^"
b111 b"
b110 f"
b101 j"
b100 n"
b11 r"
b10 v"
b11111111111111111111111111100010 !#
b100000 B
b1 "#
1?
#60000
0?
#65000
b1 e
b10 a
b11 ]
b11 [
b100000000000000100000000000000011 =
b100000000000000100000000000000011 D
b10 v"
b11 r"
b100 n"
b101 j"
b110 f"
b111 b"
b1000 ^"
b1001 Z"
b1010 V"
b1011 R"
b1100 N"
b1101 J"
b1110 F"
b1111 B"
b10000 >"
b10001 :"
b10010 6"
b10011 2"
b10100 ."
b10101 *"
b10110 &"
b10111 ""
b11000 |
b11001 x
b11010 t
b11011 p
b11100 l
b11101 h
b11110 d
b11111 `
b11111111111111111111111111100011 !#
b100000 B
b10 "#
1?
#70000
0?
#75000
b1 i
b10 e
b11 a
b100 ]
b111 [
b1000000000000001000000000000000110000000000000100 =
b1000000000000001000000000000000110000000000000100 D
b11111 `
b11110 d
b11101 h
b11100 l
b11011 p
b11010 t
b11001 x
b11000 |
b10111 ""
b10110 &"
b10101 *"
b10100 ."
b10011 2"
b10010 6"
b10001 :"
b10000 >"
b1111 B"
b1110 F"
b1101 J"
b1100 N"
b1011 R"
b1010 V"
b1001 Z"
b1000 ^"
b111 b"
b110 f"
b101 j"
b100 n"
b11 r"
b10 v"
b11111111111111111111111111100100 !#
b100000 B
b11 "#
1?
#80000
0?
#85000
b1 m
b10 i
b11 e
b100 a
b101 ]
b1111 [
b10000000000000010000000000000001100000000000001000000000000000101 =
b10000000000000010000000000000001100000000000001000000000000000101 D
b10 v"
b11 r"
b100 n"
b101 j"
b110 f"
b111 b"
b1000 ^"
b1001 Z"
b1010 V"
b1011 R"
b1100 N"
b1101 J"
b1110 F"
b1111 B"
b10000 >"
b10001 :"
b10010 6"
b10011 2"
b10100 ."
b10101 *"
b10110 &"
b10111 ""
b11000 |
b11001 x
b11010 t
b11011 p
b11100 l
b11101 h
b11110 d
b11111 `
b11111111111111111111111111100101 !#
b100000 B
b100 "#
1?
#90000
0?
#95000
b1 q
b10 m
b11 i
b100 e
b101 a
b110 ]
b11111 [
b100000000000000100000000000000011000000000000010000000000000001010000000000000110 =
b100000000000000100000000000000011000000000000010000000000000001010000000000000110 D
b11111 `
b11110 d
b11101 h
b11100 l
b11011 p
b11010 t
b11001 x
b11000 |
b10111 ""
b10110 &"
b10101 *"
b10100 ."
b10011 2"
b10010 6"
b10001 :"
b10000 >"
b1111 B"
b1110 F"
b1101 J"
b1100 N"
b1011 R"
b1010 V"
b1001 Z"
b1000 ^"
b111 b"
b110 f"
b101 j"
b100 n"
b11 r"
b10 v"
b11111111111111111111111111100110 !#
b100000 B
b101 "#
1?
#100000
0?
#105000
b1 u
b10 q
b11 m
b100 i
b101 e
b110 a
b111 ]
b111111 [
b1000000000000001000000000000000110000000000000100000000000000010100000000000001100000000000000111 =
b1000000000000001000000000000000110000000000000100000000000000010100000000000001100000000000000111 D
b10 v"
b11 r"
b100 n"
b101 j"
b110 f"
b111 b"
b1000 ^"
b1001 Z"
b1010 V"
b1011 R"
b1100 N"
b1101 J"
b1110 F"
b1111 B"
b10000 >"
b10001 :"
b10010 6"
b10011 2"
b10100 ."
b10101 *"
b10110 &"
b10111 ""
b11000 |
b11001 x
b11010 t
b11011 p
b11100 l
b11101 h
b11110 d
b11111 `
b11111111111111111111111111100111 !#
b100000 B
b110 "#
1?
#110000
0?
#115000
b1 y
b10 u
b11 q
b100 m
b101 i
b110 e
b111 a
b1000 ]
b1111111 [
b10000000000000010000000000000001100000000000001000000000000000101000000000000011000000000000001110000000000001000 =
b10000000000000010000000000000001100000000000001000000000000000101000000000000011000000000000001110000000000001000 D
b11111 `
b11110 d
b11101 h
b11100 l
b11011 p
b11010 t
b11001 x
b11000 |
b10111 ""
b10110 &"
b10101 *"
b10100 ."
b10011 2"
b10010 6"
b10001 :"
b10000 >"
b1111 B"
b1110 F"
b1101 J"
b1100 N"
b1011 R"
b1010 V"
b1001 Z"
b1000 ^"
b111 b"
b110 f"
b101 j"
b100 n"
b11 r"
b10 v"
b11111111111111111111111111101000 !#
b100000 B
b111 "#
1?
#120000
0?
